Komponenten/Decoder/decoder.vhdl
-- Laboratory RA solutions/versuch3
-- Sommersemester 25
-- Group Details
-- Lab Date:
-- 1. Participant First and Last Name: Daniel Schwenkkrauß
-- 2. Participant First and Last Name: Daniel Auberer

library ieee;
    use ieee.std_logic_1164.all;
    use ieee.numeric_std.all;
    use work.Constant_package.all;
    use work.types.all;

entity decoder is
    generic (
        g_word_width : integer := WORD_WIDTH
    );

    port (
        pi_instruction : in  std_logic_vector(g_word_width - 1 downto 0);
        po_controlWord : out controlword
    );
end entity;

architecture arc of decoder is
begin
    process (pi_instruction)
        variable v_ctrl_word : controlword;
        variable v_insFormat : t_instruction_type;
    begin
        -- Default value
        v_ctrl_word := control_word_init;

        -- Check opcode of instruction (last 6 bits) and use t_instruction_type
        case pi_instruction(6 downto 0) is
            when R_INS_OP =>
                v_insFormat := rFormat;
            when I_INS_OP =>
                v_insFormat := iFormat;
            when LUI_INS_OP =>
                v_insFormat := uFormat;
            when AUIPC_INS_OP =>
                v_insFormat := uFormat;
            when JAL_INS_OP =>
                v_insFormat := uFormat;
            when JALR_INS_OP =>
                v_insFormat := iFormat;
            when B_INS_OP =>
                v_insFormat := bFormat;
            when others =>
                v_insFormat := nullFormat;
        end case;

        case v_insFormat is
            when rFormat =>
                -- r-type instructions read rs2 and rs1 registers for source operands and
                -- write result in rd
                -- instruction in r-format uses bit 30 to differentiate between add/sub
                -- and arithmetic/logical r-shift
                -- bits 14-12 are "funct3" which sets operation type
                -- ALU opcodes match this format
                v_ctrl_word.ALU_OP := pi_instruction(30) & pi_instruction(14 downto 12);
                v_ctrl_word.REG_WRITE := '1';
            when iFormat =>
                if pi_instruction(6 downto 0) = JALR_INS_OP then
                    v_ctrl_word.ALU_OP := ADD_ALU_OP;
                    v_ctrl_word.PC_SEL := '1';
                    v_ctrl_word.WB_SEL := "10";
                else
                    -- check for SRAI and SRLI instruction where bits 31-25 mimic funct7 (special format)
                    if pi_instruction(14 downto 12) = SRL_ALU_OP(2 downto 0) then
                        v_ctrl_word.ALU_OP(3) := pi_instruction(30);
                    else
                        v_ctrl_word.ALU_OP(3) := '0';
                    end if;
                    v_ctrl_word.ALU_OP(2 downto 0) := pi_instruction(14 downto 12);
                    v_ctrl_word.WB_SEL := "00";
                end if;

                v_ctrl_word.I_IMM_SEL := '1';
                v_ctrl_word.REG_WRITE := '1';
            when uFormat =>
                v_ctrl_word.ALU_OP := ADD_ALU_OP;
                v_ctrl_word.I_IMM_SEL := '1';
                if pi_instruction(6 downto 0) = AUIPC_INS_OP then
                    v_ctrl_word.A_SEL := '1';
                    v_ctrl_word.WB_SEL := "00";
                elsif pi_instruction(6 downto 0) = JAL_INS_OP then
                    v_ctrl_word.A_SEL := '1';
                    v_ctrl_word.PC_SEL := '1';
                    v_ctrl_word.WB_SEL := "10";
                else
                    v_ctrl_word.A_SEL := '0';
                    v_ctrl_word.WB_SEL := "01";
                end if;
                v_ctrl_word.REG_WRITE := '1';
            when bFormat =>
                v_ctrl_word.IS_BRANCH := '1';
                v_ctrl_word.CMP_RESULT := '1';

                if pi_instruction(14 downto 12) = FUNC3_BEQ or
                   pi_instruction(14 downto 12) = FUNC3_BGE or
                   pi_instruction(14 downto 12) = FUNC3_BGEU then
                    v_ctrl_word.CMP_RESULT := '0';
                end if;

                if pi_instruction(14 downto 12) = FUNC3_BEQ or
                   pi_instruction(14 downto 12) = FUNC3_BNE then
                    v_ctrl_word.ALU_OP := SUB_ALU_OP;
                end if;

                if pi_instruction(14 downto 12) = FUNC3_BLT or
                   pi_instruction(14 downto 12) = FUNC3_BGE then
                    v_ctrl_word.ALU_OP := SLT_ALU_OP;
                end if;

                if pi_instruction(14 downto 12) = FUNC3_BLTU or
                   pi_instruction(14 downto 12) = FUNC3_BGEU then
                    v_ctrl_word.ALU_OP := SLTU_ALU_OP;
                end if;
            when others =>
                null;
        end case;
        po_controlWord <= v_ctrl_word;
    end process;
end architecture;

Testbenches/Decoder/decoder_tb.vhdl
library ieee;
use ieee.std_logic_1164.all;
use ieee.numeric_std.all;
use work.constant_package.all;
USE work.util_asm_package.ALL;
use work.types.all;


entity decoder_tb is
end entity decoder_tb;

architecture behavior of decoder_tb is

  constant PERIOD : time := 10 ns; -- Example: ClockPERIOD of 10 ns
  signal s_instruction : std_logic_vector(WORD_WIDTH - 1 downto 0) := (others => '0');
  signal s_controlword : controlWord := CONTROL_WORD_INIT;
  signal s_clk : std_logic := '0';

begin

  lu8 : entity work.decoder
    port map(
      pi_instruction => s_instruction,
      po_controlWord => s_controlword
    );

  lu : process is

    -- For each architecture, check if the instruction format it adds to the decoder is decoded correctly

    variable v_aluoperation : std_logic_vector(ALU_OPCODE_WIDTH - 1 downto 0) := ADD_ALU_OP;
    variable v_rs1 : integer := 5;
    variable v_rs2 : integer := 4;
    variable v_rd  : integer := 6;
    variable v_expectedcontrolword : controlWord := CONTROL_WORD_INIT;
    variable func3 : std_logic_vector(2 downto 0)              := ADD_ALU_OP(ALU_OPCODE_WIDTH - 2 downto 0);
    variable v_shamt : integer := 6;
  begin

    -- R-Format Decoding
    v_expectedControlWord := CONTROL_WORD_INIT;
    v_expectedControlWord.I_IMM_SEL := '0';
    v_expectedControlWord.ALU_OP := ADD_ALU_OP;
    v_expectedControlWord.REG_WRITE := '1';
    s_instruction <= Asm2Std("ADD",v_rd,v_rs1,v_rs2);wait for PERIOD / 2;
    assert (s_controlword = v_expectedcontrolword) report "Error in R-Format decoding"  severity error;
    
  
    v_expectedControlWord.ALU_OP := SUB_ALU_OP;
    s_instruction <=Asm2Std("SUB",v_rd,v_rs1,v_rs2);wait for PERIOD / 2;
    assert (s_controlword = v_expectedcontrolword)
    report "Error in R-Format decoding"  severity error;


    v_expectedControlWord.ALU_OP := SRA_ALU_OP;
    s_instruction <=Asm2Std("SRA",v_rd,v_rs1,v_rs2);wait for PERIOD / 2;
    assert (s_controlword = v_expectedcontrolword) report "Error in R-Format decoding"  severity error;


    v_expectedControlWord.ALU_OP := SRL_ALU_OP;
    s_instruction <= Asm2Std("SRL",v_rd,v_rs1,v_rs2);wait for PERIOD / 2;
    assert (s_controlword = v_expectedcontrolword) report "Error in R-Format decoding"  severity error;


  
    s_instruction <=Asm2Std("SLL",v_rd,v_rs1,v_rs2);wait for PERIOD / 2;
    v_expectedControlWord := CONTROL_WORD_INIT;
    v_expectedControlWord.I_IMM_SEL := '0';
    v_expectedControlWord.ALU_OP := SLL_ALU_OP;
    v_expectedControlWord.REG_WRITE := '1';
    assert (s_controlword = v_expectedcontrolword)    report "Error in R-Format decoding"  severity error;

    s_instruction <=Asm2Std("OR",v_rd,v_rs1,v_rs2);wait for PERIOD / 2;
     v_expectedControlWord := CONTROL_WORD_INIT;
     v_expectedControlWord.I_IMM_SEL := '0';
    v_expectedControlWord.ALU_OP := OR_ALU_OP;
    v_expectedControlWord.REG_WRITE := '1';
    assert (s_controlword = v_expectedcontrolword)    report "Error in R-Format decoding"  severity error;


      
    s_instruction <= Asm2Std("XOR",v_rd,v_rs1,v_rs2);wait for PERIOD / 2;
     v_expectedControlWord := CONTROL_WORD_INIT;
     v_expectedControlWord.I_IMM_SEL := '0';
    v_expectedControlWord.ALU_OP := XOR_ALU_OP;
    v_expectedControlWord.REG_WRITE := '1';
    assert (s_controlword = v_expectedcontrolword)    report "Error in R-Format decoding"  severity error;


      
    s_instruction <=Asm2Std("AND",v_rd,v_rs1,v_rs2);wait for PERIOD / 2;
     v_expectedControlWord := CONTROL_WORD_INIT;
     v_expectedControlWord.I_IMM_SEL := '0';
    v_expectedControlWord.ALU_OP := AND_ALU_OP;
    v_expectedControlWord.REG_WRITE := '1';
    assert (s_controlword = v_expectedcontrolword)    report "Error in R-Format decoding"  severity error;

    s_instruction <=Asm2Std("SLTU",v_rd,v_rs1,v_rs2);wait for PERIOD / 2;
     v_expectedControlWord := CONTROL_WORD_INIT;
     v_expectedControlWord.I_IMM_SEL := '0';
    v_expectedControlWord.ALU_OP := SLTU_ALU_OP;
    v_expectedControlWord.REG_WRITE := '1';
    assert (s_controlword = v_expectedcontrolword)    report "Error in R-Format decoding"  severity error;

  
    s_instruction <= Asm2Std("SLT",v_rd,v_rs1,v_rs2);wait for PERIOD / 2;
     v_expectedControlWord := CONTROL_WORD_INIT;
     v_expectedControlWord.I_IMM_SEL := '0';
    v_expectedControlWord.ALU_OP := SLT_ALU_OP;
    v_expectedControlWord.REG_WRITE := '1';
    assert (s_controlword = v_expectedcontrolword)    report "Error in R-Format decoding"  severity error;


--  I-Format Decoding
  
    s_instruction <=Asm2Std("ADDI",v_rd,v_rs1,v_rs2);wait for PERIOD / 2;
     v_expectedControlWord := CONTROL_WORD_INIT;
     v_expectedControlWord.I_IMM_SEL := '1';
    v_expectedControlWord.ALU_OP := ADD_ALU_OP;
    v_expectedControlWord.REG_WRITE := '1';
    assert (s_controlword = v_expectedcontrolword) report "Error in I-Format decoding"  severity error;


    s_instruction <=Asm2Std("ORI",v_rd,v_rs1,v_rs2);wait for PERIOD / 2;
     v_expectedControlWord := CONTROL_WORD_INIT;
     v_expectedControlWord.I_IMM_SEL := '1';
    v_expectedControlWord.ALU_OP := OR_ALU_OP;
    v_expectedControlWord.REG_WRITE := '1';
    assert (s_controlword = v_expectedcontrolword)    report "Error in I-Format decoding"  severity error;

    s_instruction <=Asm2Std("XORI",v_rd,v_rs1,v_rs2);wait for PERIOD / 2;
    v_expectedControlWord := CONTROL_WORD_INIT;
     v_expectedControlWord.I_IMM_SEL := '1';
    v_expectedControlWord.ALU_OP := XOR_ALU_OP;
    v_expectedControlWord.REG_WRITE := '1';
    assert (s_controlword = v_expectedcontrolword)    report "Error in I-Format decoding"  severity error;

    s_instruction <=Asm2Std("ANDI",v_rd,v_rs1,v_rs2);wait for PERIOD / 2;
    v_expectedControlWord := CONTROL_WORD_INIT;
     v_expectedControlWord.I_IMM_SEL := '1';
    v_expectedControlWord.ALU_OP := AND_ALU_OP;
    v_expectedControlWord.REG_WRITE := '1';
    assert (s_controlword = v_expectedcontrolword)    report "Error in I-Format decoding"  severity error;

    
    func3 := ADD_ALU_OP(ALU_OPCODE_WIDTH - 2 downto 0);
    s_instruction <=Asm2Std("JALR",v_rd,v_rs1,v_rs2);-- std_logic_vector(to_signed(9, 12))  & std_logic_vector(to_unsigned(v_rs1, REG_ADR_WIDTH)) & func3 & std_logic_vector(to_unsigned(v_rd, REG_ADR_WIDTH)) & JALR_INS_OP;
    wait for PERIOD / 2;
    v_expectedControlWord := CONTROL_WORD_INIT;
    v_expectedControlWord.I_IMM_SEL := '1';
    v_expectedControlWord.WB_SEL:= "10";
    v_expectedControlWord.ALU_OP := ADD_ALU_OP;
    v_expectedControlWord.PC_SEL:= '1';
    v_expectedControlWord.REG_WRITE := '1';
    assert (s_controlword = v_expectedcontrolword) report "Error in JALR-Format decoding"  severity error;


    --  U-Format Decoding

    s_instruction <=Asm2Std("LUI",v_rd,v_rs1,v_rs2);-- std_logic_vector(to_signed(9, 20)) & std_logic_vector(to_unsigned(v_rd, REG_ADR_WIDTH)) & LUI_INS_OP; 
    wait for PERIOD / 2;
     v_expectedControlWord := CONTROL_WORD_INIT;
     v_expectedControlWord.I_IMM_SEL := '1';
    v_expectedControlWord.WB_SEL:= "01";
    v_expectedControlWord.ALU_OP := ADD_ALU_OP;
    v_expectedControlWord.REG_WRITE := '1';
    assert (s_controlword = v_expectedcontrolword)    report "Error in LUI-Format decoding"  severity error;

    s_instruction <=Asm2Std("AUIPC",v_rd,v_rs1,v_rs2);-- std_logic_vector(to_signed(9, 20)) & std_logic_vector(to_unsigned(v_rd, REG_ADR_WIDTH)) & AUIPC_INS_OP; 
    wait for PERIOD / 2;
    v_expectedControlWord := CONTROL_WORD_INIT;
     v_expectedControlWord.I_IMM_SEL := '1';
    v_expectedControlWord.A_SEL:= '1';
    v_expectedControlWord.ALU_OP := ADD_ALU_OP;
    v_expectedControlWord.REG_WRITE := '1';
    assert (s_controlword = v_expectedcontrolword)    report "Error in AUIPC-Format decoding"  severity error;
    
    
    
    s_instruction <=Asm2Std("JAL",v_rd,v_rs1,v_rs2);-- std_logic_vector(to_signed(9, 20)) & std_logic_vector(to_unsigned(v_rd, REG_ADR_WIDTH)) & JAL_INS_OP; 
    wait for PERIOD / 2;
    v_expectedControlWord := CONTROL_WORD_INIT;
    v_expectedControlWord.I_IMM_SEL := '1';
    v_expectedControlWord.WB_SEL:= "10";
    v_expectedControlWord.ALU_OP := ADD_ALU_OP;
    v_expectedControlWord.PC_SEL:= '1';
    v_expectedControlWord.A_SEL:= '1';
    v_expectedControlWord.REG_WRITE := '1';
    assert (s_controlword = v_expectedcontrolword)    report "Error in JAL-Format decoding"  severity error;
    
    -- BRANCH-Format Decoding (BEQ, BNE, BLT, BGE, BLTU, BGEU)
    -- BEQ
    s_instruction <= Asm2Std("BEQ",v_rd,v_rs1,v_rs2); wait for PERIOD / 2;
    v_expectedControlWord := CONTROL_WORD_INIT;
    v_expectedControlWord.ALU_OP := SUB_ALU_OP;
    v_expectedControlWord.IS_BRANCH := '1';
    v_expectedControlWord.CMP_RESULT  := '0';
    assert (s_controlword = v_expectedcontrolword) report "Error in BEQ decoding" severity error;

    -- BNE
    s_instruction <= Asm2Std("BNE",v_rd,v_rs1,v_rs2); wait for PERIOD / 2;
    v_expectedControlWord := CONTROL_WORD_INIT;
    v_expectedControlWord.ALU_OP := SUB_ALU_OP;
    v_expectedControlWord.IS_BRANCH := '1';
    v_expectedControlWord.CMP_RESULT  := '1';
    assert (s_controlword = v_expectedcontrolword) report "Error in BNE decoding" severity error;

    -- BLT
    s_instruction <= Asm2Std("BLT",v_rd,v_rs1,v_rs2); wait for PERIOD / 2;
    v_expectedControlWord := CONTROL_WORD_INIT;
    v_expectedControlWord.ALU_OP := SLT_ALU_OP;
    v_expectedControlWord.IS_BRANCH := '1';
    v_expectedControlWord.CMP_RESULT  := '1';
    assert (s_controlword = v_expectedcontrolword) report "Error in BLT decoding" severity error;

    -- BGE
    s_instruction <= Asm2Std("BGE",v_rd,v_rs1,v_rs2); wait for PERIOD / 2;
    v_expectedControlWord := CONTROL_WORD_INIT;
    v_expectedControlWord.ALU_OP := SLT_ALU_OP;
    v_expectedControlWord.IS_BRANCH := '1';
    v_expectedControlWord.CMP_RESULT  := '0';
    assert (s_controlword = v_expectedcontrolword) report "Error in BGE decoding" severity error;

    -- BLTU
    s_instruction <= Asm2Std("BLTU",v_rd,v_rs1,v_rs2); wait for PERIOD / 2;
    v_expectedControlWord := CONTROL_WORD_INIT;
    v_expectedControlWord.ALU_OP := SLTU_ALU_OP;
    v_expectedControlWord.IS_BRANCH := '1';
    v_expectedControlWord.CMP_RESULT  := '1';
    assert (s_controlword = v_expectedcontrolword) report "Error in BLTU decoding" severity error;

    -- BGEU
    s_instruction <= Asm2Std("BGEU",v_rd,v_rs1,v_rs2); wait for PERIOD / 2;
    v_expectedControlWord := CONTROL_WORD_INIT;
    v_expectedControlWord.ALU_OP := SLTU_ALU_OP;
    v_expectedControlWord.IS_BRANCH := '1';
    v_expectedControlWord.CMP_RESULT  := '0';
    assert (s_controlword = v_expectedcontrolword) report "Error in BGEU decoding" severity error;


    -- Immediate Shift Instructions (SLLI, SRLI, SRAI)

    -- SLLI
    s_instruction <= Asm2Std("SLLI", v_rd, v_rs1, v_shamt); wait for PERIOD / 2;
    v_expectedControlWord := CONTROL_WORD_INIT;
    v_expectedControlWord.I_IMM_SEL := '1';
    v_expectedControlWord.ALU_OP := SLL_ALU_OP;
    v_expectedControlWord.REG_WRITE := '1';
    assert (s_controlword = v_expectedcontrolword)
      report "Error in I-Format decoding (SLLI)" severity error;

    -- SRLI
    s_instruction <= Asm2Std("SRLI", v_rd, v_rs1, v_shamt); wait for PERIOD / 2;
    v_expectedControlWord := CONTROL_WORD_INIT;
    v_expectedControlWord.I_IMM_SEL := '1';
    v_expectedControlWord.ALU_OP := SRL_ALU_OP;
    v_expectedControlWord.REG_WRITE := '1';
    assert (s_controlword = v_expectedcontrolword)
      report "Error in I-Format decoding (SRLI)" severity error;

    -- SRAI
    s_instruction <= Asm2Std("SRAI", v_rd, v_rs1, v_shamt); wait for PERIOD / 2;
    v_expectedControlWord := CONTROL_WORD_INIT;
    v_expectedControlWord.I_IMM_SEL := '1';
    v_expectedControlWord.ALU_OP := SRA_ALU_OP;
    v_expectedControlWord.REG_WRITE := '1';
    assert (s_controlword = v_expectedcontrolword)
      report "Error in I-Format decoding (SRAI)" severity error;




    assert false   report "End of decoder test!!!"    severity note;

    wait; --  Wait forever; this will finish the simulation.

  end process lu;

end architecture behavior;

Skripts/Decoder/decoder_debug.vcd
$date
  Tue Jun 10 17:21:20 2025
$end
$version
  GHDL v0
$end
$timescale
  1 fs
$end
$scope module standard $end
$upscope $end
$scope module textio $end
$upscope $end
$scope module std_logic_1164 $end
$upscope $end
$scope module numeric_std $end
$upscope $end
$scope module constant_package $end
$upscope $end
$scope module math_real $end
$upscope $end
$scope module types $end
$upscope $end
$scope module util_asm_package $end
$upscope $end
$scope module decoder_tb $end
$var reg 32 ! s_instruction[31:0] $end
$comment s_controlword is not handled $end
$var reg 1 " s_clk $end
$scope module lu8 $end
$var reg 32 # pi_instruction[31:0] $end
$comment po_controlword is not handled $end
$upscope $end
$upscope $end
$enddefinitions $end
#0
b00000000010000101000001100110011 !
0"
b00000000010000101000001100110011 #
#5000000
b01000000010000101000001100110011 !
b01000000010000101000001100110011 #
#10000000
b01000000010000101101001100110011 !
b01000000010000101101001100110011 #
#15000000
b00000000010000101101001100110011 !
b00000000010000101101001100110011 #
#20000000
b00000000010000101001001100110011 !
b00000000010000101001001100110011 #
#25000000
b00000000010000101110001100110011 !
b00000000010000101110001100110011 #
#30000000
b00000000010000101100001100110011 !
b00000000010000101100001100110011 #
#35000000
b00000000010000101111001100110011 !
b00000000010000101111001100110011 #
#40000000
b00000000010000101011001100110011 !
b00000000010000101011001100110011 #
#45000000
b00000000010000101010001100110011 !
b00000000010000101010001100110011 #
#50000000
b00000000010000101000001100010011 !
b00000000010000101000001100010011 #
#55000000
b00000000010000101110001100010011 !
b00000000010000101110001100010011 #
#60000000
b00000000010000101100001100010011 !
b00000000010000101100001100010011 #
#65000000
b00000000010000101111001100010011 !
b00000000010000101111001100010011 #
#70000000
b00000000010000101000001101100111 !
b00000000010000101000001101100111 #
#75000000
b00000000000000000101001100110111 !
b00000000000000000101001100110111 #
#80000000
b00000000000000000101001100010111 !
b00000000000000000101001100010111 #
#85000000
b00000000101000000000001101101111 !
b00000000101000000000001101101111 #
#90000000
b00000000010100110000010001100011 !
b00000000010100110000010001100011 #
#95000000
b00000000010100110001010001100011 !
b00000000010100110001010001100011 #
#100000000
b00000000010100110100010001100011 !
b00000000010100110100010001100011 #
#105000000
b00000000010100110101010001100011 !
b00000000010100110101010001100011 #
#110000000
b00000000010100110110010001100011 !
b00000000010100110110010001100011 #
#115000000
b00000000010100110111010001100011 !
b00000000010100110111010001100011 #
#120000000
b00000000011000101001001100010011 !
b00000000011000101001001100010011 #
#125000000
b00000000011000101101001100010011 !
b00000000011000101101001100010011 #
#130000000
b01000000011000101101001100010011 !
b01000000011000101101001100010011 #
